awsiamvault/__init__.py
awsiamvault/awsiamvault.py
awsiamvault-0.0.2.dist-info/LICENSE
awsiamvault-0.0.2.dist-info/METADATA
awsiamvault-0.0.2.dist-info/WHEEL
awsiamvault-0.0.2.dist-info/top_level.txt
awsiamvault-0.0.2.dist-info/RECORD
