Metadata-Version: 2.1
Name: awsiamvault
Version: 0.0.2
Summary: A small helper for getting a secretfrom Vault using IAM role credentials
Home-page: https://github.com/cjhodges77/aws-iam-vault
Author: Chris Hodges
Author-email: chris@humbershoe.co.uk
License: UNKNOWN
Platform: UNKNOWN
Classifier: Programming Language :: Python :: 3
Classifier: License :: OSI Approved :: GNU General Public License (GPL)
Classifier: Operating System :: OS Independent
Requires-Dist: boto3
Requires-Dist: hvac
